pypipe.py
pypipe_ppp-0.4.1.dist-info/METADATA
pypipe_ppp-0.4.1.dist-info/WHEEL
pypipe_ppp-0.4.1.dist-info/entry_points.txt
pypipe_ppp-0.4.1.dist-info/licenses/LICENSE
pypipe_ppp-0.4.1.dist-info/RECORD
