Metadata-Version: 2.1
Name: pypipe-ppp
Version: 0.4.1
Summary: A Python command-line tool for pipeline processing
Project-URL: Documentation, https://github.com/bugen/pypipe#readme
Project-URL: Issues, https://github.com/bugen/pypipe/issues
Project-URL: Source, https://github.com/bugen/pypipe
Author-email: bugen <paradise.on.paradise@gmail.com>
License-Expression: Apache-2.0
License-File: LICENSE
Classifier: Development Status :: 4 - Beta
Classifier: Programming Language :: Python
Classifier: Programming Language :: Python :: 3.6
Classifier: Programming Language :: Python :: 3.7
Classifier: Programming Language :: Python :: 3.8
Classifier: Programming Language :: Python :: 3.9
Classifier: Programming Language :: Python :: 3.10
Classifier: Programming Language :: Python :: 3.11
Classifier: Programming Language :: Python :: 3.12
Requires-Python: >=3.6
